LCCA_EnergySystems/LCCA.py
LCCA_EnergySystems/__init__.py
LCCA_EnergySystems-0.0.3.dist-info/LICENSE
LCCA_EnergySystems-0.0.3.dist-info/METADATA
LCCA_EnergySystems-0.0.3.dist-info/WHEEL
LCCA_EnergySystems-0.0.3.dist-info/top_level.txt
LCCA_EnergySystems-0.0.3.dist-info/RECORD
