Metadata-Version: 2.1
Name: LCCA_EnergySystems
Version: 0.0.3
Summary: this is a package for life cycle cost analysis for energy systems.
Author-email: mango cornerstone <mango.cornerstone@gmail.com>
Project-URL: Homepage, https://github.com/mango-cornerstone/LCCA_EnergySystems
Project-URL: Bug Tracker, https://github.com/mango-cornerstone/LCCA_EnergySystems/issues
Classifier: Programming Language :: Python :: 3
Classifier: License :: OSI Approved :: MIT License
Classifier: Operating System :: OS Independent
Requires-Python: >=3.7
License-File: LICENSE
